n_property/__init__.py
n_property/utils.py
n_property-0.0.7.dist-info/DESCRIPTION.rst
n_property-0.0.7.dist-info/METADATA
n_property-0.0.7.dist-info/RECORD
n_property-0.0.7.dist-info/WHEEL
n_property-0.0.7.dist-info/metadata.json
n_property-0.0.7.dist-info/top_level.txt
