Metadata-Version: 2.0
Name: n-property
Version: 0.0.7
Summary: To solve the N+1 problem of @property and more.
Home-page: https://github.com/hrmthw/n_property
Author: hrmthw,yetone
Author-email: UNKNOWN
License: UNKNOWN
Platform: UNKNOWN
